example/__init__.py
example/run_example.py
example/tasks/__init__.py
example/tasks/base_task.py
example/tasks/fact_customer_task.py
example/tasks/init_source_task.py
example/tests/__init__.py
sqltask/__init__.py
sqltask/classes.py
sqltask/common.py
sqltask/exceptions.py
sqltask/utils.py
sqltask/base/__init__.py
sqltask/base/common.py
sqltask/base/dq.py
sqltask/base/engine.py
sqltask/base/exceptions.py
sqltask/base/lookup_source.py
sqltask/base/row_source.py
sqltask/base/row_target.py
sqltask/base/table.py
sqltask/classes/__init__.py
sqltask/classes/common.py
sqltask/classes/context.py
sqltask/classes/dq.py
sqltask/classes/engine.py
sqltask/classes/exceptions.py
sqltask/classes/file.py
sqltask/classes/sql.py
sqltask/classes/table.py
sqltask/engine_specs/__init__.py
sqltask/engine_specs/base.py
sqltask/engine_specs/bigquery.py
sqltask/engine_specs/mssql.py
sqltask/engine_specs/postgresql.py
sqltask/engine_specs/snowflake.py
sqltask/engine_specs/sqlite.py
sqltask/examples/__init__.py
sqltask/examples/customer.py
sqltask/sources/__init__.py
sqltask/sources/csv.py
sqltask/sources/generic.py
sqltask/sources/sql.py
sqltask/utils/__init__.py
sqltask/utils/engine_specs.py
sqltask/utils/file.py
sqltask-0.5.2.dist-info/LICENSE
sqltask-0.5.2.dist-info/METADATA
sqltask-0.5.2.dist-info/WHEEL
sqltask-0.5.2.dist-info/top_level.txt
sqltask-0.5.2.dist-info/RECORD
