Metadata-Version: 2.1
Name: sqltask
Version: 0.5.2
Summary: ETL tool based on SqlAlchemy for building robust ETL pipelies with high emphasis on high data quality
Home-page: https://github.com/villebro/sqltask
Author: Ville Brofeldt
Author-email: villebro@apache.org
License: MIT
Platform: UNKNOWN
Classifier: Programming Language :: Python
Classifier: Programming Language :: Python :: 3
Classifier: Programming Language :: Python :: 3.6
Classifier: Programming Language :: Python :: 3.7
Classifier: Programming Language :: Python :: 3.8
Classifier: Intended Audience :: Developers
Classifier: License :: OSI Approved :: MIT License
Classifier: Natural Language :: English
Requires-Dist: sqlalchemy
Requires-Dist: chardet
Provides-Extra: bigquery
Requires-Dist: pybigquery (>=0.4.11) ; extra == 'bigquery'
Provides-Extra: mssql
Requires-Dist: pymssql (>=2.1.4) ; extra == 'mssql'
Provides-Extra: postgres
Requires-Dist: psycopg2 (>=2.8.3) ; extra == 'postgres'
Provides-Extra: snowflake
Requires-Dist: snowflake-sqlalchemy (>=1.1.14) ; extra == 'snowflake'
